pycotore/__init__.py
pycotore/converter.py
pycotore/exceptions.py
pycotore/logger.py
pycotore/progress.py
pycotore-0.2.3.dist-info/LICENSE
pycotore-0.2.3.dist-info/METADATA
pycotore-0.2.3.dist-info/WHEEL
pycotore-0.2.3.dist-info/RECORD
