Metadata-Version: 2.1
Name: pycotore
Version: 0.2.3
Summary: Generic classes for reuse
Home-page: https://github.com/niekosau
License: GPL-3.0-only
Author: Arunas Grigalionis
Author-email: arunas.grigalionis@gmail.com
Requires-Python: >=3.9,<3.10
Classifier: License :: OSI Approved :: GNU General Public License v3 (GPLv3)
Classifier: Programming Language :: Python :: 3
Classifier: Programming Language :: Python :: 3.9
Project-URL: Repository, https://github.com/niekosau/pycotore
